{"zip_code":"25023","locality":"SALTILLO","federal_entity":{"key":5,"name":"COAHUILA DE ZARAGOZA","code":null},"settlements":[{"key":95,"name":"UNIVERSIDAD PUEBLO","zone_type":"URBANO","settlement_type":{"name":"Colonia"}},{"key":369,"name":"MONTEVISTA","zone_type":"URBANO","settlement_type":{"name":"Fraccionamiento"}},{"key":457,"name":"CANTABRIA","zone_type":"URBANO","settlement_type":{"name":"Fraccionamiento"}},{"key":1740,"name":"LA PALMA","zone_type":"URBANO","settlement_type":{"name":"Colonia"}},{"key":1741,"name":"EL PARAISO","zone_type":"URBANO","settlement_type":{"name":"Colonia"}},{"key":1742,"name":"SAN VICENTE","zone_type":"URBANO","settlement_type":{"name":"Colonia"}},{"key":1750,"name":"ARBOLEDAS POPULAR","zone_type":"URBANO","settlement_type":{"name":"Colonia"}},{"key":1751,"name":"LOMA BONITA","zone_type":"URBANO","settlement_type":{"name":"Colonia"}},{"key":2399,"name":"VALLE DE LAS PALMAS","zone_type":"URBANO","settlement_type":{"name":"Colonia"}},{"key":2585,"name":"VALLE DE SANTA ELENA","zone_type":"URBANO","settlement_type":{"name":"Fraccionamiento"}},{"key":3215,"name":"LA ROSALEDA","zone_type":"URBANO","settlement_type":{"name":"Fraccionamiento"}}],"municipality":{"key":30,"name":"SALTILLO"}}