{"zip_code":"25303","locality":"","federal_entity":{"key":5,"name":"COAHUILA DE ZARAGOZA","code":null},"settlements":[{"key":274,"name":"RANCHO NUEVO","zone_type":"RURAL","settlement_type":{"name":"Ejido"}},{"key":279,"name":"CHAPULA","zone_type":"RURAL","settlement_type":{"name":"Ejido"}},{"key":280,"name":"SAN BLAS","zone_type":"RURAL","settlement_type":{"name":"Ejido"}},{"key":281,"name":"SANTA RITA","zone_type":"RURAL","settlement_type":{"name":"Ejido"}}],"municipality":{"key":30,"name":"SALTILLO"}}