{"zip_code":"28784","locality":"","federal_entity":{"key":6,"name":"COLIMA","code":null},"settlements":[{"key":295,"name":"POTRERO GRANDE","zone_type":"RURAL","settlement_type":{"name":"Rancheria"}},{"key":298,"name":"LAS GUASIMAS","zone_type":"RURAL","settlement_type":{"name":"Rancheria"}},{"key":299,"name":"EL NOGAL","zone_type":"RURAL","settlement_type":{"name":"Rancheria"}},{"key":300,"name":"AGUA FRIA","zone_type":"RURAL","settlement_type":{"name":"Rancheria"}}],"municipality":{"key":8,"name":"MINATITLAN"}}