{"zip_code":"29064","locality":"TUXTLA GUTIERREZ","federal_entity":{"key":7,"name":"CHIAPAS","code":null},"settlements":[{"key":177,"name":"LINDAVISTA","zone_type":"URBANO","settlement_type":{"name":"Fraccionamiento"}},{"key":281,"name":"LAS FUENTES","zone_type":"URBANO","settlement_type":{"name":"Fraccionamiento"}},{"key":282,"name":"JARDINES DE MACTUMATZA","zone_type":"URBANO","settlement_type":{"name":"Fraccionamiento"}},{"key":2833,"name":"MANUEL MOLANO","zone_type":"URBANO","settlement_type":{"name":"Fraccionamiento"}},{"key":2904,"name":"LA GLORIA","zone_type":"URBANO","settlement_type":{"name":"Colonia"}},{"key":3565,"name":"SAN JOSE LIBRAMIENTO","zone_type":"URBANO","settlement_type":{"name":"Colonia"}}],"municipality":{"key":101,"name":"TUXTLA GUTIERREZ"}}