{"zip_code":"29323","locality":"","federal_entity":{"key":7,"name":"CHIAPAS","code":null},"settlements":[{"key":5,"name":"TRES CRUCES","zone_type":"RURAL","settlement_type":{"name":"Colonia"}},{"key":19,"name":"LOMHO I","zone_type":"RURAL","settlement_type":{"name":"Colonia"}},{"key":22,"name":"TZALATOM","zone_type":"RURAL","settlement_type":{"name":"Colonia"}},{"key":27,"name":"BAHOSIL","zone_type":"RURAL","settlement_type":{"name":"Colonia"}},{"key":35,"name":"ARVENZA DOS","zone_type":"RURAL","settlement_type":{"name":"Colonia"}},{"key":48,"name":"UKUMTIC","zone_type":"RURAL","settlement_type":{"name":"Colonia"}},{"key":50,"name":"BAUTISTA GRANDE","zone_type":"RURAL","settlement_type":{"name":"Colonia"}},{"key":57,"name":"AGUA AZUL","zone_type":"RURAL","settlement_type":{"name":"Colonia"}},{"key":58,"name":"JECHBOTIK","zone_type":"RURAL","settlement_type":{"name":"Colonia"}},{"key":62,"name":"YAKAMPOT (YOKPOT)","zone_type":"RURAL","settlement_type":{"name":"Colonia"}},{"key":403,"name":"CATISHTIC","zone_type":"RURAL","settlement_type":{"name":"Pueblo"}},{"key":416,"name":"SANTA ANA","zone_type":"RURAL","settlement_type":{"name":"Pueblo"}},{"key":424,"name":"ARVENZA UNO","zone_type":"RURAL","settlement_type":{"name":"Colonia"}},{"key":425,"name":"BAUTISTA CHICO","zone_type":"RURAL","settlement_type":{"name":"Colonia"}},{"key":426,"name":"LOMHO","zone_type":"RURAL","settlement_type":{"name":"Colonia"}},{"key":427,"name":"NARVAEZ","zone_type":"RURAL","settlement_type":{"name":"Rancheria"}},{"key":2852,"name":"CUCHULUMTIC","zone_type":"RURAL","settlement_type":{"name":"Colonia"}}],"municipality":{"key":23,"name":"CHAMULA"}}