{"zip_code":"34573","locality":"","federal_entity":{"key":10,"name":"DURANGO","code":null},"settlements":[{"key":5316,"name":"ARROYO DEL OSO","zone_type":"RURAL","settlement_type":{"name":"Rancheria"}},{"key":5320,"name":"EL PINITO DE OSOS BRAVOS [ASERRADERO]","zone_type":"RURAL","settlement_type":{"name":"Rancheria"}},{"key":5356,"name":"EL AGUAJE","zone_type":"RURAL","settlement_type":{"name":"Rancheria"}},{"key":5366,"name":"EL ARROYO DEL OSO","zone_type":"RURAL","settlement_type":{"name":"Rancheria"}},{"key":5412,"name":"EL GATUNAL","zone_type":"RURAL","settlement_type":{"name":"Rancheria"}},{"key":5478,"name":"EL POLEYAL DE SANTA ANA","zone_type":"RURAL","settlement_type":{"name":"Rancheria"}},{"key":5484,"name":"EL POTRERITO","zone_type":"RURAL","settlement_type":{"name":"Rancheria"}},{"key":5501,"name":"EL PUERTO DE LA CIENEGA","zone_type":"RURAL","settlement_type":{"name":"Rancheria"}},{"key":5506,"name":"EL RANCHITO","zone_type":"RURAL","settlement_type":{"name":"Pueblo"}},{"key":5507,"name":"EL RANCHITO","zone_type":"RURAL","settlement_type":{"name":"Rancheria"}},{"key":5526,"name":"EL SALTO","zone_type":"RURAL","settlement_type":{"name":"Rancheria"}},{"key":5551,"name":"EL VAINILLO","zone_type":"RURAL","settlement_type":{"name":"Rancheria"}},{"key":5560,"name":"HACIENDA DE CAMARONES","zone_type":"RURAL","settlement_type":{"name":"Rancheria"}},{"key":5563,"name":"LA ACEQUIA (QUEBRADA DE LOS LORA)","zone_type":"RURAL","settlement_type":{"name":"Rancheria"}},{"key":5577,"name":"LA CANADA","zone_type":"RURAL","settlement_type":{"name":"Rancheria"}},{"key":5581,"name":"LA CEBADILLA","zone_type":"RURAL","settlement_type":{"name":"Rancheria"}},{"key":5583,"name":"LA CEBADILLITA","zone_type":"RURAL","settlement_type":{"name":"Rancheria"}},{"key":5586,"name":"LA CIENEGA","zone_type":"RURAL","settlement_type":{"name":"Rancheria"}},{"key":5590,"name":"LA CIENEGA DE LA SIRENA","zone_type":"RURAL","settlement_type":{"name":"Rancheria"}},{"key":5597,"name":"LA CIENEGUITA","zone_type":"RURAL","settlement_type":{"name":"Rancheria"}},{"key":5598,"name":"LA CONTRAYERBA","zone_type":"RURAL","settlement_type":{"name":"Rancheria"}},{"key":5603,"name":"LA CRUZ DE SANTA ANA","zone_type":"RURAL","settlement_type":{"name":"Rancheria"}},{"key":5614,"name":"LA HACIENDITA","zone_type":"RURAL","settlement_type":{"name":"Rancheria"}},{"key":5626,"name":"LA JOYA DE ABAJO","zone_type":"RURAL","settlement_type":{"name":"Rancheria"}},{"key":5657,"name":"LA MESITA DE SANTA ANA","zone_type":"RURAL","settlement_type":{"name":"Rancheria"}},{"key":5675,"name":"LA ROSITA","zone_type":"RURAL","settlement_type":{"name":"Rancheria"}},{"key":5682,"name":"LA SIRENA","zone_type":"RURAL","settlement_type":{"name":"Rancheria"}},{"key":5720,"name":"LAS HABAS","zone_type":"RURAL","settlement_type":{"name":"Rancheria"}},{"key":5743,"name":"LAS MESAS DE LA CONCEPCION","zone_type":"RURAL","settlement_type":{"name":"Rancheria"}},{"key":5764,"name":"LOS AGUAJES","zone_type":"RURAL","settlement_type":{"name":"Rancheria"}},{"key":5766,"name":"LOS AGUAJITOS","zone_type":"RURAL","settlement_type":{"name":"Rancheria"}},{"key":5787,"name":"LOS DESMONTES","zone_type":"RURAL","settlement_type":{"name":"Rancheria"}},{"key":5792,"name":"LOS INMORTALES","zone_type":"RURAL","settlement_type":{"name":"Rancheria"}},{"key":5795,"name":"LOS LAURELES","zone_type":"RURAL","settlement_type":{"name":"Rancheria"}},{"key":5807,"name":"LOS PARAJES","zone_type":"RURAL","settlement_type":{"name":"Rancheria"}},{"key":5827,"name":"MESA DE LAS PALMAS","zone_type":"RURAL","settlement_type":{"name":"Rancheria"}},{"key":5836,"name":"OSOS BRAVOS","zone_type":"RURAL","settlement_type":{"name":"Rancheria"}},{"key":5869,"name":"RANCHO ESCONDIDO","zone_type":"RURAL","settlement_type":{"name":"Rancheria"}},{"key":5879,"name":"SAN ANATOLIO","zone_type":"RURAL","settlement_type":{"name":"Rancheria"}},{"key":5888,"name":"SAN DARIO","zone_type":"RURAL","settlement_type":{"name":"Rancheria"}},{"key":5919,"name":"SANTA ANA","zone_type":"RURAL","settlement_type":{"name":"Rancheria"}},{"key":5925,"name":"SANTA GERTRUDIS","zone_type":"RURAL","settlement_type":{"name":"Rancheria"}},{"key":5927,"name":"SANTA ROSITA","zone_type":"RURAL","settlement_type":{"name":"Rancheria"}}],"municipality":{"key":34,"name":"TAMAZULA"}}