{"zip_code":"36237","locality":"","federal_entity":{"key":11,"name":"GUANAJUATO","code":null},"settlements":[{"key":108,"name":"CALDERONES","zone_type":"RURAL","settlement_type":{"name":"Pueblo"}},{"key":6938,"name":"CARBONERA","zone_type":"RURAL","settlement_type":{"name":"Rancheria"}},{"key":6943,"name":"CHICHINDARO","zone_type":"RURAL","settlement_type":{"name":"Rancheria"}},{"key":6947,"name":"OLIMPO (CASAS BLANCAS)","zone_type":"RURAL","settlement_type":{"name":"Colonia"}},{"key":6984,"name":"EL TROMPETERO (CERRO DEL TROMPETERO)","zone_type":"RURAL","settlement_type":{"name":"Rancheria"}},{"key":6998,"name":"GRANJA SAN MARTIN (SUBIDA A LA CUESTA)","zone_type":"RURAL","settlement_type":{"name":"Rancheria"}},{"key":7079,"name":"PRESA DE MATA","zone_type":"RURAL","settlement_type":{"name":"Rancheria"}},{"key":7123,"name":"UCEA CAMPUS MARFIL","zone_type":"RURAL","settlement_type":{"name":"Equipamiento"}}],"municipality":{"key":15,"name":"GUANAJUATO"}}