{"zip_code":"39075","locality":"CHILPANCINGO DE LOS BRAVO","federal_entity":{"key":12,"name":"GUERRERO","code":null},"settlements":[{"key":145,"name":"VILLA DE LAS FLORES","zone_type":"URBANO","settlement_type":{"name":"Colonia"}},{"key":1698,"name":"UNIVERSITARIOS UNIDOS POR GUERRERO","zone_type":"URBANO","settlement_type":{"name":"Colonia"}},{"key":4100,"name":"14 DE FEBRERO","zone_type":"URBANO","settlement_type":{"name":"Colonia"}}],"municipality":{"key":29,"name":"CHILPANCINGO DE LOS BRAVO"}}