{"zip_code":"40060","locality":"IGUALA DE LA INDEPENDENCIA","federal_entity":{"key":12,"name":"GUERRERO","code":null},"settlements":[{"key":1828,"name":"ADOLFO LOPEZ MATEOS","zone_type":"URBANO","settlement_type":{"name":"Colonia"}},{"key":1829,"name":"JARDINES","zone_type":"URBANO","settlement_type":{"name":"Colonia"}},{"key":1830,"name":"RUFFO FIGUEROA","zone_type":"URBANO","settlement_type":{"name":"Colonia"}},{"key":1832,"name":"UNIDOS POR GUERRERO","zone_type":"URBANO","settlement_type":{"name":"Colonia"}},{"key":1833,"name":"20 DE NOVIEMBRE","zone_type":"URBANO","settlement_type":{"name":"Colonia"}},{"key":4057,"name":"JARDINES DE SAN ANDRES","zone_type":"URBANO","settlement_type":{"name":"Colonia"}},{"key":4164,"name":"PLAN DE IGUALA","zone_type":"URBANO","settlement_type":{"name":"Colonia"}},{"key":4166,"name":"FLORIDA","zone_type":"URBANO","settlement_type":{"name":"Colonia"}},{"key":4306,"name":"MEZQUITAL","zone_type":"URBANO","settlement_type":{"name":"Colonia"}},{"key":4595,"name":"LOS PINOS","zone_type":"URBANO","settlement_type":{"name":"Colonia"}}],"municipality":{"key":35,"name":"IGUALA DE LA INDEPENDENCIA"}}