{"zip_code":"40080","locality":"IGUALA DE LA INDEPENDENCIA","federal_entity":{"key":12,"name":"GUERRERO","code":null},"settlements":[{"key":2,"name":"ALBERTO ROMAN ARELLANO","zone_type":"URBANO","settlement_type":{"name":"Colonia"}},{"key":1844,"name":"CNOP","zone_type":"URBANO","settlement_type":{"name":"Colonia"}},{"key":1845,"name":"24 DE FEBRERO","zone_type":"URBANO","settlement_type":{"name":"Colonia"}},{"key":1846,"name":"VICENTE GUERRERO","zone_type":"URBANO","settlement_type":{"name":"Colonia"}},{"key":4059,"name":"EL CAPIRE","zone_type":"URBANO","settlement_type":{"name":"Colonia"}},{"key":4156,"name":"DEL SEGURO SOCIAL","zone_type":"URBANO","settlement_type":{"name":"Colonia"}},{"key":4157,"name":"COSMOS","zone_type":"URBANO","settlement_type":{"name":"Colonia"}},{"key":4158,"name":"CAMINO BLANCO","zone_type":"URBANO","settlement_type":{"name":"Fraccionamiento"}},{"key":4219,"name":"CAMPESTRE ALTAMIRA","zone_type":"URBANO","settlement_type":{"name":"Colonia"}}],"municipality":{"key":35,"name":"IGUALA DE LA INDEPENDENCIA"}}