{"zip_code":"43004","locality":"","federal_entity":{"key":13,"name":"HIDALGO","code":null},"settlements":[{"key":1096,"name":"SANTA CRUZ","zone_type":"URBANO","settlement_type":{"name":"Pueblo"}},{"key":1097,"name":"SITLAN","zone_type":"RURAL","settlement_type":{"name":"Rancheria"}},{"key":1119,"name":"CECECAPA","zone_type":"RURAL","settlement_type":{"name":"Rancheria"}},{"key":1120,"name":"CUATECOMETL","zone_type":"URBANO","settlement_type":{"name":"Pueblo"}},{"key":1121,"name":"LA MESA DE LIMANTITLA","zone_type":"RURAL","settlement_type":{"name":"Rancheria"}},{"key":4648,"name":"ATEIXCO","zone_type":"RURAL","settlement_type":{"name":"Rancheria"}},{"key":4654,"name":"CAPANE","zone_type":"RURAL","settlement_type":{"name":"Rancheria"}},{"key":4656,"name":"CHACHAIXPA","zone_type":"RURAL","settlement_type":{"name":"Rancheria"}},{"key":4697,"name":"LOS PARAJES BENITO JUAREZ","zone_type":"RURAL","settlement_type":{"name":"Rancheria"}},{"key":4752,"name":"ZOHUALA","zone_type":"RURAL","settlement_type":{"name":"Rancheria"}}],"municipality":{"key":28,"name":"HUEJUTLA DE REYES"}}