{"zip_code":"43852","locality":"","federal_entity":{"key":13,"name":"HIDALGO","code":null},"settlements":[{"key":1932,"name":"SANTA MARIA TECAJETE","zone_type":"URBANO","settlement_type":{"name":"Pueblo"}},{"key":1933,"name":"FRANCISCO VILLA","zone_type":"URBANO","settlement_type":{"name":"Pueblo"}},{"key":1935,"name":"EX-HACIENDA DE TECAJETE","zone_type":"RURAL","settlement_type":{"name":"Rancheria"}},{"key":6404,"name":"LAS PALOMAS","zone_type":"RURAL","settlement_type":{"name":"Rancheria"}},{"key":6415,"name":"LA PROVIDENCIA","zone_type":"RURAL","settlement_type":{"name":"Rancheria"}},{"key":6419,"name":"LAS LOMAS (LOS GALLEROS)","zone_type":"RURAL","settlement_type":{"name":"Rancheria"}},{"key":6421,"name":"EL TEJAMANIL","zone_type":"RURAL","settlement_type":{"name":"Rancheria"}}],"municipality":{"key":83,"name":"ZEMPOALA"}}