{"zip_code":"51517","locality":"","federal_entity":{"key":15,"name":"MEXICO","code":null},"settlements":[{"key":1245,"name":"SAN SIMON (SAN SIMON ZOZOCOLTEPEC)","zone_type":"RURAL","settlement_type":{"name":"Pueblo"}},{"key":1257,"name":"TEPEHUAJES UNO (TEPEHUAJES DE ARRIBA)","zone_type":"RURAL","settlement_type":{"name":"Pueblo"}},{"key":7653,"name":"TEPEHUAJES (TEPEHUAJES DE ABAJO)","zone_type":"RURAL","settlement_type":{"name":"Rancheria"}},{"key":7654,"name":"LA PAROTA (LA PAROTA TEPEHUAJES)","zone_type":"RURAL","settlement_type":{"name":"Rancheria"}}],"municipality":{"key":8,"name":"AMATEPEC"}}