{"zip_code":"54770","locality":"","federal_entity":{"key":15,"name":"MEXICO","code":null},"settlements":[{"key":5132,"name":"TLATILCO","zone_type":"URBANO","settlement_type":{"name":"Barrio"}},{"key":5134,"name":"TLATENCO","zone_type":"URBANO","settlement_type":{"name":"Barrio"}},{"key":7083,"name":"MISIONES TEOLOYUCAN","zone_type":"URBANO","settlement_type":{"name":"Fraccionamiento"}},{"key":7084,"name":"VILLAS TEOLOYUCAN","zone_type":"URBANO","settlement_type":{"name":"Fraccionamiento"}},{"key":7994,"name":"HACIENDA BEATRIZ","zone_type":"URBANO","settlement_type":{"name":"Fraccionamiento"}}],"municipality":{"key":91,"name":"TEOLOYUCAN"}}