{"zip_code":"56343","locality":"CHIMALHUACAN","federal_entity":{"key":15,"name":"MEXICO","code":null},"settlements":[{"key":4231,"name":"SUTAUR ORIENTE","zone_type":"URBANO","settlement_type":{"name":"Fraccionamiento"}},{"key":4232,"name":"SAN JOSE BUENAVISTA","zone_type":"URBANO","settlement_type":{"name":"Fraccionamiento"}},{"key":4233,"name":"VILLA SAN AGUSTIN ATLAPULCO","zone_type":"URBANO","settlement_type":{"name":"Colonia"}},{"key":4234,"name":"JARDINES DE SAN AGUSTIN (LA ISLA, SANCHO GANADERO)","zone_type":"URBANO","settlement_type":{"name":"Colonia"}},{"key":4236,"name":"MIRAMAR","zone_type":"URBANO","settlement_type":{"name":"Colonia"}},{"key":4237,"name":"TEQUESQUINAHUAC","zone_type":"URBANO","settlement_type":{"name":"Colonia"}},{"key":4238,"name":"TIERRA SANTA (MARAVILLAS)","zone_type":"URBANO","settlement_type":{"name":"Fraccionamiento"}},{"key":4239,"name":"BALCONES DE SAN AGUSTIN","zone_type":"URBANO","settlement_type":{"name":"Colonia"}},{"key":4240,"name":"AMPLIACION SAN AGUSTIN","zone_type":"URBANO","settlement_type":{"name":"Colonia"}},{"key":4242,"name":"AMPLIACION SAN AGUSTIN ZONA PONIENTE","zone_type":"URBANO","settlement_type":{"name":"Colonia"}},{"key":4624,"name":"ZONA COMUNAL SAN AGUSTIN","zone_type":"URBANO","settlement_type":{"name":"Colonia"}},{"key":4669,"name":"DIECISIETE DE MARZO","zone_type":"RURAL","settlement_type":{"name":"Colonia"}},{"key":4673,"name":"ISRAEL","zone_type":"URBANO","settlement_type":{"name":"Colonia"}},{"key":4675,"name":"LOS OLIVOS","zone_type":"URBANO","settlement_type":{"name":"Fraccionamiento"}},{"key":4991,"name":"BUENOS AIRES","zone_type":"URBANO","settlement_type":{"name":"Colonia"}},{"key":4992,"name":"ADOLFO LOPEZ MATEOS","zone_type":"URBANO","settlement_type":{"name":"Colonia"}},{"key":7870,"name":"AMPLIACION SAN AGUSTIN ZONA ORIENTE","zone_type":"URBANO","settlement_type":{"name":"Colonia"}}],"municipality":{"key":31,"name":"CHIMALHUACAN"}}