{"zip_code":"59669","locality":"ZAMORA DE HIDALGO","federal_entity":{"key":16,"name":"MICHOACAN DE OCAMPO","code":null},"settlements":[{"key":1351,"name":"LINDAVISTA","zone_type":"URBANO","settlement_type":{"name":"Fraccionamiento"}},{"key":3792,"name":"HACIENDA DEL VALLE","zone_type":"URBANO","settlement_type":{"name":"Fraccionamiento"}},{"key":4424,"name":"JAVIER TAMAYO","zone_type":"URBANO","settlement_type":{"name":"Colonia"}},{"key":4438,"name":"MEMO GOMEZ LINDAVISTA","zone_type":"URBANO","settlement_type":{"name":"Colonia"}},{"key":4441,"name":"NUEVA ESPERANZA","zone_type":"URBANO","settlement_type":{"name":"Colonia"}},{"key":4442,"name":"NUEVA MARGARITA","zone_type":"URBANO","settlement_type":{"name":"Colonia"}},{"key":4907,"name":"LA HUIZACHERA","zone_type":"URBANO","settlement_type":{"name":"Colonia"}}],"municipality":{"key":108,"name":"ZAMORA"}}