{"zip_code":"60884","locality":"","federal_entity":{"key":16,"name":"MICHOACAN DE OCAMPO","code":null},"settlements":[{"key":28,"name":"BEJUCO DEL COIRE","zone_type":"RURAL","settlement_type":{"name":"Rancho"}},{"key":47,"name":"COIRE","zone_type":"RURAL","settlement_type":{"name":"Rancheria"}},{"key":48,"name":"COIRE VIEJO","zone_type":"RURAL","settlement_type":{"name":"Rancho"}},{"key":65,"name":"EL AGUACATE","zone_type":"RURAL","settlement_type":{"name":"Rancho"}},{"key":70,"name":"EL ALGODON","zone_type":"RURAL","settlement_type":{"name":"Rancho"}},{"key":71,"name":"EL APALMAR","zone_type":"RURAL","settlement_type":{"name":"Rancho"}},{"key":85,"name":"EL CAYACO","zone_type":"RURAL","settlement_type":{"name":"Rancho"}},{"key":88,"name":"EL CHICO","zone_type":"RURAL","settlement_type":{"name":"Rancho"}},{"key":97,"name":"EL DIEZMO","zone_type":"RURAL","settlement_type":{"name":"Rancho"}},{"key":106,"name":"EL IZOTE","zone_type":"RURAL","settlement_type":{"name":"Rancho"}},{"key":119,"name":"EL OCOTE","zone_type":"RURAL","settlement_type":{"name":"Rancho"}},{"key":137,"name":"EL SAUZ DEL ALGODON","zone_type":"RURAL","settlement_type":{"name":"Rancho"}},{"key":140,"name":"EL TERRERO","zone_type":"RURAL","settlement_type":{"name":"Rancho"}},{"key":150,"name":"GUAGUARIAMA (GUARIAMA)","zone_type":"RURAL","settlement_type":{"name":"Rancho"}},{"key":156,"name":"HUITZIRALDO DEL COIRE","zone_type":"RURAL","settlement_type":{"name":"Rancho"}},{"key":167,"name":"LA CIENEGA DEL DIEZMO","zone_type":"RURAL","settlement_type":{"name":"Rancho"}},{"key":168,"name":"LA COFRADIA DE COIRE","zone_type":"RURAL","settlement_type":{"name":"Rancho"}},{"key":174,"name":"LA CUCHARA DEL DIEZMO","zone_type":"RURAL","settlement_type":{"name":"Rancho"}},{"key":175,"name":"LA CUEVA","zone_type":"RURAL","settlement_type":{"name":"Rancho"}},{"key":176,"name":"LA CUIDARA","zone_type":"RURAL","settlement_type":{"name":"Rancho"}},{"key":191,"name":"LA LOMBRICERA","zone_type":"RURAL","settlement_type":{"name":"Rancho"}},{"key":207,"name":"LA PENA","zone_type":"RURAL","settlement_type":{"name":"Rancho"}},{"key":225,"name":"LAS JUNTAS","zone_type":"RURAL","settlement_type":{"name":"Rancho"}},{"key":240,"name":"LOS COCOS","zone_type":"RURAL","settlement_type":{"name":"Rancho"}},{"key":251,"name":"MARIALITO","zone_type":"RURAL","settlement_type":{"name":"Rancho"}},{"key":258,"name":"MUERTO ZACATE","zone_type":"RURAL","settlement_type":{"name":"Rancho"}},{"key":268,"name":"PERRICOLA","zone_type":"RURAL","settlement_type":{"name":"Rancho"}},{"key":275,"name":"CLARA","zone_type":"RURAL","settlement_type":{"name":"Rancho"}},{"key":277,"name":"VIEJO","zone_type":"RURAL","settlement_type":{"name":"Rancho"}},{"key":291,"name":"VAINILLA DEL COIRE","zone_type":"RURAL","settlement_type":{"name":"Rancho"}},{"key":294,"name":"ZILAPA","zone_type":"RURAL","settlement_type":{"name":"Rancho"}},{"key":297,"name":"EL AVIARE","zone_type":"RURAL","settlement_type":{"name":"Rancho"}},{"key":2005,"name":"ESTOPILA","zone_type":"RURAL","settlement_type":{"name":"Rancheria"}}],"municipality":{"key":8,"name":"AQUILA"}}