{"zip_code":"60924","locality":"","federal_entity":{"key":16,"name":"MICHOACAN DE OCAMPO","code":null},"settlements":[{"key":19,"name":"BUENAVISTA","zone_type":"RURAL","settlement_type":{"name":"Rancho"}},{"key":3888,"name":"EL ZAPOTE DE TOSCANO","zone_type":"RURAL","settlement_type":{"name":"Rancheria"}},{"key":5757,"name":"CHIQUIHUITILLO","zone_type":"RURAL","settlement_type":{"name":"Rancheria"}},{"key":5786,"name":"EL CHICHARRON","zone_type":"RURAL","settlement_type":{"name":"Rancheria"}},{"key":5794,"name":"EL CORDON ALTO","zone_type":"RURAL","settlement_type":{"name":"Rancheria"}},{"key":5800,"name":"EL ENCINO","zone_type":"RURAL","settlement_type":{"name":"Rancheria"}},{"key":5811,"name":"EL LIMON DE TAMAYO (LIMON DE LOS FRANCO)","zone_type":"RURAL","settlement_type":{"name":"Rancheria"}},{"key":5820,"name":"EL MULETO","zone_type":"RURAL","settlement_type":{"name":"Rancheria"}},{"key":5834,"name":"EL PINO GORDO","zone_type":"RURAL","settlement_type":{"name":"Rancheria"}},{"key":5847,"name":"EL SAUCITO","zone_type":"RURAL","settlement_type":{"name":"Rancheria"}},{"key":5852,"name":"EL TAMARINDO","zone_type":"RURAL","settlement_type":{"name":"Rancheria"}},{"key":5854,"name":"EL TUZON","zone_type":"RURAL","settlement_type":{"name":"Rancheria"}},{"key":5863,"name":"FERRERIA (FIERRERIA)","zone_type":"RURAL","settlement_type":{"name":"Rancheria"}},{"key":5874,"name":"LA AGUACATERA","zone_type":"RURAL","settlement_type":{"name":"Rancheria"}},{"key":5879,"name":"LA BOTIJA","zone_type":"RURAL","settlement_type":{"name":"Rancheria"}},{"key":5896,"name":"LA HUERTA","zone_type":"RURAL","settlement_type":{"name":"Rancheria"}},{"key":5903,"name":"LA MEDINA","zone_type":"RURAL","settlement_type":{"name":"Rancheria"}},{"key":5905,"name":"LA MESA DE LOS HORCONES","zone_type":"RURAL","settlement_type":{"name":"Rancheria"}},{"key":5908,"name":"LA MOCHA","zone_type":"RURAL","settlement_type":{"name":"Rancheria"}},{"key":5910,"name":"LA NEGRA","zone_type":"RURAL","settlement_type":{"name":"Rancheria"}},{"key":5916,"name":"LA PALMITA","zone_type":"RURAL","settlement_type":{"name":"Rancheria"}},{"key":5924,"name":"LA PENITA","zone_type":"RURAL","settlement_type":{"name":"Rancheria"}},{"key":5928,"name":"LA PLAYA","zone_type":"RURAL","settlement_type":{"name":"Rancheria"}},{"key":5930,"name":"LA RAIZUDA","zone_type":"RURAL","settlement_type":{"name":"Rancheria"}},{"key":5936,"name":"LA VAINILLERA","zone_type":"RURAL","settlement_type":{"name":"Rancheria"}},{"key":5946,"name":"LAS CAMELINAS","zone_type":"RURAL","settlement_type":{"name":"Rancheria"}},{"key":5981,"name":"LAS LAJAS","zone_type":"RURAL","settlement_type":{"name":"Rancheria"}},{"key":5992,"name":"LOS CHUPADEROS","zone_type":"RURAL","settlement_type":{"name":"Rancheria"}},{"key":6001,"name":"LOS HUIZACHES","zone_type":"RURAL","settlement_type":{"name":"Rancheria"}},{"key":6024,"name":"POTRERILLOS","zone_type":"RURAL","settlement_type":{"name":"Rancheria"}},{"key":6034,"name":"TOSCANO","zone_type":"RURAL","settlement_type":{"name":"Rancheria"}}],"municipality":{"key":10,"name":"ARTEAGA"}}