{"zip_code":"61924","locality":"","federal_entity":{"key":16,"name":"MICHOACAN DE OCAMPO","code":null},"settlements":[{"key":20,"name":"EL AGUACATE","zone_type":"RURAL","settlement_type":{"name":"Rancheria"}},{"key":31,"name":"EL JUNCO","zone_type":"RURAL","settlement_type":{"name":"Rancheria"}},{"key":33,"name":"EL MANGUITO","zone_type":"RURAL","settlement_type":{"name":"Rancheria"}},{"key":35,"name":"EL NIETO","zone_type":"RURAL","settlement_type":{"name":"Rancheria"}},{"key":44,"name":"EL SAUZ","zone_type":"RURAL","settlement_type":{"name":"Rancheria"}},{"key":48,"name":"EL VALLECILLO","zone_type":"RURAL","settlement_type":{"name":"Rancheria"}},{"key":51,"name":"EL ZAPOTE DE LOS HERRERA","zone_type":"RURAL","settlement_type":{"name":"Rancheria"}},{"key":56,"name":"LA BEJUQUERA","zone_type":"RURAL","settlement_type":{"name":"Rancheria"}},{"key":57,"name":"LA BOLUDA","zone_type":"RURAL","settlement_type":{"name":"Rancheria"}},{"key":63,"name":"LA PADILLA","zone_type":"RURAL","settlement_type":{"name":"Rancheria"}},{"key":64,"name":"LA PALMITA","zone_type":"RURAL","settlement_type":{"name":"Rancheria"}},{"key":87,"name":"LOS TEJONES","zone_type":"RURAL","settlement_type":{"name":"Rancheria"}},{"key":89,"name":"PASO DE LA VIRGEN","zone_type":"RURAL","settlement_type":{"name":"Rancheria"}},{"key":104,"name":"SAN RAFAEL","zone_type":"RURAL","settlement_type":{"name":"Rancho"}},{"key":110,"name":"EL LIMONCITO","zone_type":"RURAL","settlement_type":{"name":"Rancho"}},{"key":112,"name":"LA PILITA","zone_type":"RURAL","settlement_type":{"name":"Rancho"}},{"key":115,"name":"LA CEIBA GUICHA","zone_type":"RURAL","settlement_type":{"name":"Rancho"}}],"municipality":{"key":13,"name":"CARACUARO"}}