{"zip_code":"66646","locality":"CIUDAD APODACA","federal_entity":{"key":19,"name":"NUEVO LEON","code":null},"settlements":[{"key":2,"name":"RESIDENCIAL SAN BENITO","zone_type":"URBANO","settlement_type":{"name":"Fraccionamiento"}},{"key":62,"name":"SANTA SOFIA RESIDENCIAL","zone_type":"URBANO","settlement_type":{"name":"Fraccionamiento"}},{"key":79,"name":"MONTEBELLO HUINALA","zone_type":"URBANO","settlement_type":{"name":"Fraccionamiento"}},{"key":1436,"name":"PUEBLO NUEVO","zone_type":"URBANO","settlement_type":{"name":"Colonia"}},{"key":2801,"name":"PORTAL DE HUINALA","zone_type":"URBANO","settlement_type":{"name":"Colonia"}},{"key":2806,"name":"MILENIUM RESIDENCIAL","zone_type":"URBANO","settlement_type":{"name":"Colonia"}},{"key":2807,"name":"SAN ISIDRO","zone_type":"URBANO","settlement_type":{"name":"Fraccionamiento"}},{"key":3175,"name":"MISION DE HUINALA","zone_type":"URBANO","settlement_type":{"name":"Fraccionamiento"}},{"key":3466,"name":"MISION DE SAN JAVIER","zone_type":"URBANO","settlement_type":{"name":"Colonia"}},{"key":3528,"name":"SAN JAVIER","zone_type":"URBANO","settlement_type":{"name":"Colonia"}},{"key":4083,"name":"TREBOLES","zone_type":"URBANO","settlement_type":{"name":"Fraccionamiento"}},{"key":4088,"name":"PRIVADA DOMINIO","zone_type":"URBANO","settlement_type":{"name":"Fraccionamiento"}},{"key":4100,"name":"PRIVADAS CANTERAS","zone_type":"URBANO","settlement_type":{"name":"Fraccionamiento"}},{"key":4148,"name":"RIVERAS DE HUINALA","zone_type":"URBANO","settlement_type":{"name":"Colonia"}},{"key":4149,"name":"LOS COLIBRIES","zone_type":"URBANO","settlement_type":{"name":"Colonia"}},{"key":4151,"name":"LOMAS DE SAN ISIDRO","zone_type":"URBANO","settlement_type":{"name":"Colonia"}},{"key":4154,"name":"PRIVALIA HUINALA","zone_type":"URBANO","settlement_type":{"name":"Fraccionamiento"}},{"key":5095,"name":"TERRANOVA ELITE","zone_type":"URBANO","settlement_type":{"name":"Fraccionamiento"}}],"municipality":{"key":6,"name":"APODACA"}}