{"zip_code":"69200","locality":"","federal_entity":{"key":20,"name":"OAXACA","code":null},"settlements":[{"key":946,"name":"EL PERU","zone_type":"RURAL","settlement_type":{"name":"Barrio"}},{"key":947,"name":"EL REFUGIO","zone_type":"RURAL","settlement_type":{"name":"Barrio"}},{"key":948,"name":"EL ROSARIO","zone_type":"RURAL","settlement_type":{"name":"Barrio"}},{"key":950,"name":"EL SOCORRITO","zone_type":"RURAL","settlement_type":{"name":"Barrio"}},{"key":1265,"name":"SAN JOSE","zone_type":"RURAL","settlement_type":{"name":"Barrio"}},{"key":1282,"name":"SAN SEBASTIAN","zone_type":"RURAL","settlement_type":{"name":"Barrio"}},{"key":1488,"name":"TEZOATLAN DE SEGURA Y LUNA","zone_type":"RURAL","settlement_type":{"name":"Pueblo"}}],"municipality":{"key":549,"name":"TEZOATLAN DE SEGURA Y LUNA"}}