{"zip_code":"70680","locality":"SALINA CRUZ","federal_entity":{"key":20,"name":"OAXACA","code":null},"settlements":[{"key":1050,"name":"ISTMENA","zone_type":"URBANO","settlement_type":{"name":"Colonia"}},{"key":2337,"name":"CANTARRANAS","zone_type":"URBANO","settlement_type":{"name":"Barrio"}},{"key":2339,"name":"LA SOLEDAD","zone_type":"URBANO","settlement_type":{"name":"Colonia"}},{"key":2340,"name":"LAS BRISAS","zone_type":"URBANO","settlement_type":{"name":"Colonia"}},{"key":2341,"name":"SAN JUAN","zone_type":"URBANO","settlement_type":{"name":"Colonia"}},{"key":2342,"name":"SAN MARTIN","zone_type":"URBANO","settlement_type":{"name":"Colonia"}},{"key":3577,"name":"MIRAMAR","zone_type":"URBANO","settlement_type":{"name":"Colonia"}},{"key":4212,"name":"ENSENADA LA VENTOSA","zone_type":"URBANO","settlement_type":{"name":"Pueblo"}}],"municipality":{"key":79,"name":"SALINA CRUZ"}}