{"zip_code":"72707","locality":"CUAUTLANCINGO","federal_entity":{"key":21,"name":"PUEBLA","code":null},"settlements":[{"key":6912,"name":"IPANEMA","zone_type":"URBANO","settlement_type":{"name":"Residencial"}},{"key":6929,"name":"MAYORCA","zone_type":"URBANO","settlement_type":{"name":"Residencial"}},{"key":6949,"name":"TRIBECA","zone_type":"URBANO","settlement_type":{"name":"Residencial"}},{"key":6958,"name":"VILLAS DEL ALTO","zone_type":"URBANO","settlement_type":{"name":"Conjunto habitacional"}}],"municipality":{"key":41,"name":"CUAUTLANCINGO"}}