{"zip_code":"73274","locality":"","federal_entity":{"key":21,"name":"PUEBLA","code":null},"settlements":[{"key":902,"name":"EL ENCINAL","zone_type":"RURAL","settlement_type":{"name":"Rancheria"}},{"key":7959,"name":"ORO VERDE (MONTE DE CHILA)","zone_type":"RURAL","settlement_type":{"name":"Rancheria"}},{"key":7962,"name":"ARROYO HONDO","zone_type":"RURAL","settlement_type":{"name":"Rancheria"}},{"key":7963,"name":"LA CONCHA","zone_type":"RURAL","settlement_type":{"name":"Rancheria"}}],"municipality":{"key":89,"name":"JOPALA"}}