{"zip_code":"73700","locality":"","federal_entity":{"key":21,"name":"PUEBLA","code":null},"settlements":[{"key":1,"name":"SANTA ANITA","zone_type":"URBANO","settlement_type":{"name":"Colonia"}},{"key":2,"name":"XALEHUALA","zone_type":"URBANO","settlement_type":{"name":"Colonia"}},{"key":3,"name":"EL PORVENIR","zone_type":"URBANO","settlement_type":{"name":"Colonia"}},{"key":1215,"name":"ACUACO","zone_type":"URBANO","settlement_type":{"name":"Colonia"}},{"key":1216,"name":"LAS TRANCAS","zone_type":"RURAL","settlement_type":{"name":"Pueblo"}},{"key":1217,"name":"ZARAGOZA","zone_type":"RURAL","settlement_type":{"name":"Pueblo"}}],"municipality":{"key":211,"name":"ZARAGOZA"}}