{"zip_code":"76775","locality":"","federal_entity":{"key":22,"name":"QUERETARO","code":null},"settlements":[{"key":601,"name":"BORDO BLANCO","zone_type":"URBANO","settlement_type":{"name":"Pueblo"}},{"key":1829,"name":"SANTA MARIA DEL CAMINO","zone_type":"URBANO","settlement_type":{"name":"Colonia"}},{"key":2541,"name":"LAS CORRALETAS","zone_type":"URBANO","settlement_type":{"name":"Colonia"}},{"key":2544,"name":"LA ERMITA","zone_type":"URBANO","settlement_type":{"name":"Colonia"}},{"key":2553,"name":"CERRITO SAN JOSE","zone_type":"URBANO","settlement_type":{"name":"Colonia"}}],"municipality":{"key":17,"name":"TEQUISQUIAPAN"}}