{"zip_code":"78049","locality":"SAN LUIS POTOSI","federal_entity":{"key":24,"name":"SAN LUIS POTOSI","code":null},"settlements":[{"key":24,"name":"SANTIAGO DEL RIO","zone_type":"URBANO","settlement_type":{"name":"Barrio"}},{"key":75,"name":"SANTIAGO DEL RIO","zone_type":"URBANO","settlement_type":{"name":"Fraccionamiento"}},{"key":1947,"name":"HUERTA REAL","zone_type":"URBANO","settlement_type":{"name":"Fraccionamiento"}},{"key":2061,"name":"FRESNOS DEL RIO","zone_type":"URBANO","settlement_type":{"name":"Fraccionamiento"}},{"key":2250,"name":"PRIVADA RESIDENCIAL REAL DE ALVAREZ","zone_type":"URBANO","settlement_type":{"name":"Fraccionamiento"}},{"key":2251,"name":"CONJUNTO PEDRO MORENO","zone_type":"URBANO","settlement_type":{"name":"Fraccionamiento"}},{"key":2252,"name":"VILLAS DE PEDRO MORENO","zone_type":"URBANO","settlement_type":{"name":"Fraccionamiento"}},{"key":2302,"name":"PRIVADA ALTAMIRANO","zone_type":"URBANO","settlement_type":{"name":"Fraccionamiento"}},{"key":2326,"name":"RESIDENCIAL LAS MORAS","zone_type":"URBANO","settlement_type":{"name":"Fraccionamiento"}}],"municipality":{"key":28,"name":"SAN LUIS POTOSI"}}