{"zip_code":"82270","locality":"","federal_entity":{"key":25,"name":"SINALOA","code":null},"settlements":[{"key":50,"name":"EL MILAGRO","zone_type":"RURAL","settlement_type":{"name":"Rancho"}},{"key":51,"name":"EL MIRABAL","zone_type":"RURAL","settlement_type":{"name":"Rancho"}},{"key":52,"name":"EL CANON DE BATOPILAS","zone_type":"RURAL","settlement_type":{"name":"Rancho"}},{"key":1147,"name":"EL HABAL","zone_type":"RURAL","settlement_type":{"name":"Hacienda"}}],"municipality":{"key":12,"name":"MAZATLAN"}}