{"zip_code":"85536","locality":"","federal_entity":{"key":26,"name":"SONORA","code":null},"settlements":[{"key":8,"name":"AVESTRUCES DEL NOROESTE","zone_type":"RURAL","settlement_type":{"name":"Rancheria"}},{"key":21,"name":"LA CHOYA DOS","zone_type":"RURAL","settlement_type":{"name":"Rancheria"}},{"key":30,"name":"NARCISO MENDOZA","zone_type":"RURAL","settlement_type":{"name":"Ejido"}},{"key":1329,"name":"ANTONIO ROSALES","zone_type":"RURAL","settlement_type":{"name":"Ejido"}}],"municipality":{"key":25,"name":"EMPALME"}}