{"zip_code":"86486","locality":"","federal_entity":{"key":27,"name":"TABASCO","code":null},"settlements":[{"key":10,"name":"LAS NUEVAS ESPERANZAS","zone_type":"RURAL","settlement_type":{"name":"Ejido"}},{"key":19,"name":"LAS ESPERANZAS","zone_type":"RURAL","settlement_type":{"name":"Rancheria"}},{"key":25,"name":"JUAN ESCUTIA","zone_type":"RURAL","settlement_type":{"name":"Rancheria"}},{"key":3050,"name":"POBLADO C-33 20 DE NOVIEMBRE","zone_type":"URBANO","settlement_type":{"name":"Pueblo"}}],"municipality":{"key":2,"name":"CARDENAS"}}