{"zip_code":"87256","locality":"","federal_entity":{"key":28,"name":"TAMAULIPAS","code":null},"settlements":[{"key":6,"name":"CAMPO NUMERO UNO (CAMPO ALTO)","zone_type":"RURAL","settlement_type":{"name":"Rancho"}},{"key":7,"name":"LAJILLA DEL SUR (LA LAJILLA)","zone_type":"RURAL","settlement_type":{"name":"Rancho"}},{"key":9,"name":"CAMPO NUMERO DOS","zone_type":"RURAL","settlement_type":{"name":"Rancho"}},{"key":14,"name":"CAMPO NUMERO TRES","zone_type":"RURAL","settlement_type":{"name":"Rancheria"}}],"municipality":{"key":8,"name":"CASAS"}}