{"zip_code":"89358","locality":"TAMPICO","federal_entity":{"key":28,"name":"TAMAULIPAS","code":null},"settlements":[{"key":1651,"name":"LAS TORRES","zone_type":"URBANO","settlement_type":{"name":"Colonia"}},{"key":2058,"name":"JARDINES DE CHAMPAYAN 1","zone_type":"URBANO","settlement_type":{"name":"Fraccionamiento"}},{"key":2115,"name":"MIRADORES DE LA PRESA","zone_type":"URBANO","settlement_type":{"name":"Colonia"}},{"key":2176,"name":"TIERRA ALTA","zone_type":"URBANO","settlement_type":{"name":"Colonia"}},{"key":2964,"name":"LUIS DONALDO COLOSIO","zone_type":"URBANO","settlement_type":{"name":"Colonia"}},{"key":3538,"name":"LUIS DONALDO COLOSIO","zone_type":"URBANO","settlement_type":{"name":"Fraccionamiento"}},{"key":3598,"name":"INDEPENDENCIA","zone_type":"URBANO","settlement_type":{"name":"Colonia"}},{"key":3670,"name":"VALLE ESCONDIDO","zone_type":"URBANO","settlement_type":{"name":"Fraccionamiento"}},{"key":3677,"name":"GLADIOLAS","zone_type":"URBANO","settlement_type":{"name":"Fraccionamiento"}}],"municipality":{"key":38,"name":"TAMPICO"}}