{"zip_code":"90380","locality":"APIZACO","federal_entity":{"key":29,"name":"TLAXCALA","code":null},"settlements":[{"key":196,"name":"AGRICOLA COVADONGA","zone_type":"URBANO","settlement_type":{"name":"Colonia"}},{"key":197,"name":"JARDINES DE APIZACO","zone_type":"URBANO","settlement_type":{"name":"Fraccionamiento"}},{"key":198,"name":"LA SOLEDAD","zone_type":"URBANO","settlement_type":{"name":"Fraccionamiento"}},{"key":857,"name":"EL LLANO","zone_type":"URBANO","settlement_type":{"name":"Fraccionamiento"}}],"municipality":{"key":5,"name":"APIZACO"}}