{"zip_code":"95464","locality":"","federal_entity":{"key":30,"name":"VERACRUZ DE IGNACIO DE LA LLAVE","code":null},"settlements":[{"key":6,"name":"LOS PINOS","zone_type":"URBANO","settlement_type":{"name":"Colonia"}},{"key":7,"name":"MIGUEL ALEMAN VALDEZ","zone_type":"URBANO","settlement_type":{"name":"Colonia"}},{"key":12,"name":"SALVADOR DIAZ MIRON","zone_type":"URBANO","settlement_type":{"name":"Colonia"}},{"key":15,"name":"SANTA CRUZ","zone_type":"URBANO","settlement_type":{"name":"Colonia"}}],"municipality":{"key":178,"name":"TLACOTALPAN"}}