{"zip_code":"96387","locality":"","federal_entity":{"key":30,"name":"VERACRUZ DE IGNACIO DE LA LLAVE","code":null},"settlements":[{"key":3815,"name":"EL COLORADO","zone_type":"RURAL","settlement_type":{"name":"Rancheria"}},{"key":3816,"name":"GAVILAN NORTE (SANTA ROSA)","zone_type":"RURAL","settlement_type":{"name":"Rancheria"}},{"key":3820,"name":"FRANCISCO VILLA","zone_type":"RURAL","settlement_type":{"name":"Colonia"}},{"key":3821,"name":"LA ESPERANZA","zone_type":"RURAL","settlement_type":{"name":"Pueblo"}},{"key":7569,"name":"EL PENON","zone_type":"RURAL","settlement_type":{"name":"Colonia"}}],"municipality":{"key":39,"name":"COATZACOALCOS"}}