{"zip_code":"96940","locality":"","federal_entity":{"key":30,"name":"VERACRUZ DE IGNACIO DE LA LLAVE","code":null},"settlements":[{"key":2,"name":"LA TROPICAL","zone_type":"RURAL","settlement_type":{"name":"Pueblo"}},{"key":9,"name":"EL PROGRESO","zone_type":"RURAL","settlement_type":{"name":"Pueblo"}},{"key":4000,"name":"PRIMERO DE MAYO","zone_type":"RURAL","settlement_type":{"name":"Ejido"}},{"key":4001,"name":"VICENTE GUERRERO","zone_type":"RURAL","settlement_type":{"name":"Rancheria"}},{"key":4014,"name":"BENITO JUAREZ","zone_type":"RURAL","settlement_type":{"name":"Rancheria"}},{"key":7767,"name":"LAS CONCHAS (LA COLONIA)","zone_type":"RURAL","settlement_type":{"name":"Congregacion"}}],"municipality":{"key":70,"name":"HIDALGOTITLAN"}}