{"zip_code":"98959","locality":"","federal_entity":{"key":32,"name":"ZACATECAS","code":null},"settlements":[{"key":6,"name":"EL CHINO","zone_type":"RURAL","settlement_type":{"name":"Pueblo"}},{"key":9,"name":"LA PACHONA (SAN ANDRES)","zone_type":"RURAL","settlement_type":{"name":"Rancheria"}},{"key":15,"name":"SAN JOSE DE LA VENTA","zone_type":"RURAL","settlement_type":{"name":"Rancheria"}},{"key":50,"name":"LA PURISIMA","zone_type":"RURAL","settlement_type":{"name":"Rancheria"}},{"key":408,"name":"EL PEDREGOSO","zone_type":"URBANO","settlement_type":{"name":"Pueblo"}},{"key":409,"name":"ESTANCIA DE GUADALUPE","zone_type":"RURAL","settlement_type":{"name":"Pueblo"}},{"key":410,"name":"LA LOBENA","zone_type":"RURAL","settlement_type":{"name":"Rancheria"}},{"key":1748,"name":"SAN MANUEL","zone_type":"RURAL","settlement_type":{"name":"Rancheria"}}],"municipality":{"key":38,"name":"PINOS"}}